<?xml version="1.0" encoding="UTF-8"?>
<objects serializationModel="Studio.02.03.00">
	<object class="AudioFile" id="{9aa71494-bf6d-4340-b279-9b328b5e05ee}">
		<property name="assetPath">
			<value>INTRO/SFX/Pedro/FX_InsectoA_02.wav</value>
		</property>
		<property name="frequencyInKHz">
			<value>48</value>
		</property>
		<property name="channelCount">
			<value>1</value>
		</property>
		<property name="length">
			<value>4.6962708333333332</value>
		</property>
		<relationship name="masterAssetFolder">
			<destination>{adfc6319-1cf1-4faa-ba1e-4d2c0dda1d97}</destination>
		</relationship>
	</object>
</objects>
