<?xml version="1.0" encoding="UTF-8"?>
<objects serializationModel="Studio.02.03.00">
	<object class="AudioFile" id="{fc5111e1-e597-4e13-af34-ca6096c5daf3}">
		<property name="assetPath">
			<value>INTRO/SFX/Pedro/FX_InsectoH_13.wav</value>
		</property>
		<property name="frequencyInKHz">
			<value>48</value>
		</property>
		<property name="channelCount">
			<value>1</value>
		</property>
		<property name="length">
			<value>1.1044583333333333</value>
		</property>
		<relationship name="masterAssetFolder">
			<destination>{adfc6319-1cf1-4faa-ba1e-4d2c0dda1d97}</destination>
		</relationship>
	</object>
</objects>
